hk_finance_mcp_server/__init__.py
hk_finance_mcp_server/__main__.py
hk_finance_mcp_server/app.py
hk_finance_mcp_server/tool_business_reg.py
hk_finance_mcp_server/tool_coin_cart.py
hk_finance_mcp_server/tool_credit_card.py
hk_finance_mcp_server/tool_neg_resident_mortgage.py
hk_finance_mcp_server-0.1.6.dist-info/licenses/LICENSE
hk_finance_mcp_server-0.1.6.dist-info/METADATA
hk_finance_mcp_server-0.1.6.dist-info/WHEEL
hk_finance_mcp_server-0.1.6.dist-info/entry_points.txt
hk_finance_mcp_server-0.1.6.dist-info/top_level.txt
hk_finance_mcp_server-0.1.6.dist-info/RECORD
